[
    {
        "type": "message",
        "subtype": "bot_message",
        "text": "<http:\/\/status.aws.amazon.com\/|Informational message:  Increased Launch Error Rates>\nWe are investigating increased error rates for new launches in the EU-WEST-1 Region.",
        "ts": "1537952032.000100",
        "username": "Amazon Web Services Service Status",
        "icons": {
            "image_36": "https:\/\/a.slack-edge.com\/66f9\/img\/services\/rss_36.png",
            "image_48": "https:\/\/a.slack-edge.com\/66f9\/img\/services\/rss_48.png",
            "image_72": "https:\/\/a.slack-edge.com\/205a\/img\/services\/rss_72.png"
        },
        "bot_id": "B22KL8J4T"
    },
    {
        "type": "message",
        "subtype": "bot_message",
        "text": "<http:\/\/status.aws.amazon.com\/|Informational message: Network Connectivity>\nWe can confirm increased API error rates and connectivity issues for some instances in a single Availability Zone in the EU-WEST-1 Region.",
        "ts": "1537952032.000200",
        "username": "Amazon Web Services Service Status",
        "icons": {
            "image_36": "https:\/\/a.slack-edge.com\/66f9\/img\/services\/rss_36.png",
            "image_48": "https:\/\/a.slack-edge.com\/66f9\/img\/services\/rss_48.png",
            "image_72": "https:\/\/a.slack-edge.com\/205a\/img\/services\/rss_72.png"
        },
        "bot_id": "B22KL8J4T"
    },
    {
        "type": "message",
        "subtype": "bot_message",
        "text": "<http:\/\/status.aws.amazon.com\/|Informational message: Network Connectivity>\nWe continue to investigate connectivity issues from some instances to some AWS services in the EU-WEST-1 Region. We have identified the root cause and are taking steps to resolve the issue.",
        "ts": "1537953823.000100",
        "username": "Amazon Web Services Service Status",
        "icons": {
            "image_36": "https:\/\/a.slack-edge.com\/66f9\/img\/services\/rss_36.png",
            "image_48": "https:\/\/a.slack-edge.com\/66f9\/img\/services\/rss_48.png",
            "image_72": "https:\/\/a.slack-edge.com\/205a\/img\/services\/rss_72.png"
        },
        "bot_id": "B22KL8J4T"
    },
    {
        "type": "message",
        "subtype": "bot_message",
        "text": "<http:\/\/status.aws.amazon.com\/|Informational message: Network Connectivity>\nWe have resolved the connectivity issues from EC2 instances to the affected AWS services in the EU-WEST-1 Region. We continue to see elevated error rates for the RunInstances EC2 API, which we are working to resolve. Internet connectivity and connectivity between EC2 instances remain unaffected.",
        "ts": "1537956523.000100",
        "username": "Amazon Web Services Service Status",
        "icons": {
            "image_36": "https:\/\/a.slack-edge.com\/66f9\/img\/services\/rss_36.png",
            "image_48": "https:\/\/a.slack-edge.com\/66f9\/img\/services\/rss_48.png",
            "image_72": "https:\/\/a.slack-edge.com\/205a\/img\/services\/rss_72.png"
        },
        "bot_id": "B22KL8J4T"
    },
    {
        "type": "message",
        "subtype": "bot_message",
        "text": "<http:\/\/status.aws.amazon.com\/|Informational message: Connectivity issues>\nWe are continuing to investigate connectivity issues impacting CloudHSM and CloudHSM Classic HSMs in a single Availability Zone in EU-WEST-1 Region.",
        "ts": "1537957430.000100",
        "username": "Amazon Web Services Service Status",
        "icons": {
            "image_36": "https:\/\/a.slack-edge.com\/66f9\/img\/services\/rss_36.png",
            "image_48": "https:\/\/a.slack-edge.com\/66f9\/img\/services\/rss_48.png",
            "image_72": "https:\/\/a.slack-edge.com\/205a\/img\/services\/rss_72.png"
        },
        "bot_id": "B22KL8J4T"
    },
    {
        "type": "message",
        "subtype": "bot_message",
        "text": "<http:\/\/status.aws.amazon.com\/|Service is operating normally: [RESOLVED] Network Connectivity>\nStarting at 12:15 AM PDT we experienced increased API error rates for the EC2 API, and connectivity issues between EC2 instances and AWS services in the EU-WEST-1 Region. At 2:29 AM PDT, the connectivity issues between EC2 instances and AWS services were resolved. At 2:59 AM PDT, the increased API error rates for the EC2 APIs were fully resolved. Internet connectivity and connectivity between EC2 instances was not affected. The issue has been resolved and the service is operating normally.",
        "ts": "1537959216.000100",
        "username": "Amazon Web Services Service Status",
        "icons": {
            "image_36": "https:\/\/a.slack-edge.com\/66f9\/img\/services\/rss_36.png",
            "image_48": "https:\/\/a.slack-edge.com\/66f9\/img\/services\/rss_48.png",
            "image_72": "https:\/\/a.slack-edge.com\/205a\/img\/services\/rss_72.png"
        },
        "bot_id": "B22KL8J4T"
    },
    {
        "type": "message",
        "subtype": "bot_message",
        "text": "<http:\/\/status.aws.amazon.com\/|Informational message: Connectivity issues>\nWe can confirm that current generation CloudHSM instances are operating normally. CloudHSM Classic instances in a single Availability Zone in the EU-WEST-1 Region are experiencing network connectivity errors. We are continuing to work to recover connectivity to these instances.",
        "ts": "1537959216.000200",
        "username": "Amazon Web Services Service Status",
        "icons": {
            "image_36": "https:\/\/a.slack-edge.com\/66f9\/img\/services\/rss_36.png",
            "image_48": "https:\/\/a.slack-edge.com\/66f9\/img\/services\/rss_48.png",
            "image_72": "https:\/\/a.slack-edge.com\/205a\/img\/services\/rss_72.png"
        },
        "bot_id": "B22KL8J4T"
    },
    {
        "type": "message",
        "subtype": "bot_message",
        "text": "<http:\/\/status.aws.amazon.com\/|Service is operating normally: [RESOLVED] Network Connectivity>\nBetween 12:15 AM and 2:12 AM PDT, we experienced increased error rates for console requests in EU-WEST-1 Region. The issue has been resolved and the service is now operating normally.",
        "ts": "1537961020.000100",
        "username": "Amazon Web Services Service Status",
        "icons": {
            "image_36": "https:\/\/a.slack-edge.com\/66f9\/img\/services\/rss_36.png",
            "image_48": "https:\/\/a.slack-edge.com\/66f9\/img\/services\/rss_48.png",
            "image_72": "https:\/\/a.slack-edge.com\/205a\/img\/services\/rss_72.png"
        },
        "bot_id": "B22KL8J4T"
    },
    {
        "type": "message",
        "subtype": "bot_message",
        "text": "<http:\/\/status.aws.amazon.com\/|Service is operating normally: [RESOLVED] Network Connectivity>\nBetween 12:15 AM and 2:29 AM PDT, we experienced increased packet loss, impacting AWS Direct Connect connectivity for some customers in the EU-WEST-1 Region. The issue has been resolved and the service is now operating normally.",
        "ts": "1537961020.000200",
        "username": "Amazon Web Services Service Status",
        "icons": {
            "image_36": "https:\/\/a.slack-edge.com\/66f9\/img\/services\/rss_36.png",
            "image_48": "https:\/\/a.slack-edge.com\/66f9\/img\/services\/rss_48.png",
            "image_72": "https:\/\/a.slack-edge.com\/205a\/img\/services\/rss_72.png"
        },
        "bot_id": "B22KL8J4T"
    }
]